spakky/plugins/fastapi/__init__.py
spakky/plugins/fastapi/error.py
spakky/plugins/fastapi/main.py
spakky/plugins/fastapi/middlewares/__init__.py
spakky/plugins/fastapi/middlewares/error_handling.py
spakky/plugins/fastapi/post_processors/__init__.py
spakky/plugins/fastapi/post_processors/add_builtin_middlewares.py
spakky/plugins/fastapi/post_processors/bind_lifespan.py
spakky/plugins/fastapi/post_processors/register_routes.py
spakky/plugins/fastapi/py.typed
spakky/plugins/fastapi/routes/__init__.py
spakky/plugins/fastapi/routes/delete.py
spakky/plugins/fastapi/routes/get.py
spakky/plugins/fastapi/routes/head.py
spakky/plugins/fastapi/routes/options.py
spakky/plugins/fastapi/routes/patch.py
spakky/plugins/fastapi/routes/post.py
spakky/plugins/fastapi/routes/put.py
spakky/plugins/fastapi/routes/route.py
spakky/plugins/fastapi/routes/websocket.py
spakky/plugins/fastapi/stereotypes/__init__.py
spakky/plugins/fastapi/stereotypes/api_controller.py
spakky_fastapi-5.0.1.dist-info/WHEEL
spakky_fastapi-5.0.1.dist-info/entry_points.txt
spakky_fastapi-5.0.1.dist-info/METADATA
spakky_fastapi-5.0.1.dist-info/RECORD
