Metadata-Version: 2.3
Name: spakky-fastapi
Version: 5.0.1
Summary: FastAPI plugin for Spakky framework
Author: Spakky
Author-email: Spakky <sejong418@icloud.com>
License: MIT
Requires-Dist: fastapi[standard]>=0.122.0
Requires-Dist: orjson>=3.11.4
Requires-Dist: spakky>=5.0.1
Requires-Dist: websockets>=15.0.1
Requires-Python: >=3.11
